cdk8s_aws_load_balancer_controller/__init__.py
cdk8s_aws_load_balancer_controller/py.typed
cdk8s_aws_load_balancer_controller/_jsii/__init__.py
cdk8s_aws_load_balancer_controller/_jsii/cdk8s-aws-load-balancer-controller@2.3.6.jsii.tgz
cdk8s_aws_load_balancer_controller-2.3.6.dist-info/LICENSE
cdk8s_aws_load_balancer_controller-2.3.6.dist-info/METADATA
cdk8s_aws_load_balancer_controller-2.3.6.dist-info/WHEEL
cdk8s_aws_load_balancer_controller-2.3.6.dist-info/top_level.txt
cdk8s_aws_load_balancer_controller-2.3.6.dist-info/RECORD
