Metadata-Version: 2.1
Name: cdk8s-aws-load-balancer-controller
Version: 2.3.6
Summary: cdk8s-aws-load-balancer-controller is an CDK8S construct library that provides AWS Alb Load Balancer Controller Configure.
Home-page: https://github.com/neilkuan/cdk8s-aws-load-balancer-controller.git
Author: Neil Kuan<guan840912@gmail.com>
License: Apache-2.0
Project-URL: Source, https://github.com/neilkuan/cdk8s-aws-load-balancer-controller.git
Platform: UNKNOWN
Classifier: Intended Audience :: Developers
Classifier: Operating System :: OS Independent
Classifier: Programming Language :: JavaScript
Classifier: Programming Language :: Python :: 3 :: Only
Classifier: Programming Language :: Python :: 3.6
Classifier: Programming Language :: Python :: 3.7
Classifier: Programming Language :: Python :: 3.8
Classifier: Programming Language :: Python :: 3.9
Classifier: Typing :: Typed
Classifier: Development Status :: 5 - Production/Stable
Classifier: License :: OSI Approved
Requires-Python: >=3.6
License-File: LICENSE
Requires-Dist: aws-cdk.aws-iam (<2.0.0,>=1.113.0)
Requires-Dist: aws-cdk.core (<2.0.0,>=1.113.0)
Requires-Dist: cdk8s (==1.0.0.b10)
Requires-Dist: constructs (<4.0.0,>=3.3.147)
Requires-Dist: jsii (<2.0.0,>=1.34.0)
Requires-Dist: publication (>=0.0.3)
